Arifpay_Plugin/.env
Arifpay_Plugin/ArifPay.py
Arifpay_Plugin/__init__.py
arifpay_plugin-1.0.0.dist-info/METADATA
arifpay_plugin-1.0.0.dist-info/WHEEL
arifpay_plugin-1.0.0.dist-info/RECORD
