Metadata-Version: 2.1
Name: Arifpay_Plugin
Version: 1.0.0
Summary: A python plugin for Arifpay
Author-email: Ananiya Belew <anewscho@gmail.com>
Classifier: License :: OSI Approved :: MIT License
Classifier: Operating System :: OS Independent
Classifier: Programming Language :: Python :: 3
Requires-Python: >=3.8
